slimHTTP/__init__.py
slimHTTP/core.py
slimHTTP/examples/REST_api.py
slimHTTP/examples/discord_bot_and_web.py
slimHTTP/examples/http_server.py
slimHTTP/examples/http_websocket.py
slimHTTP/examples/https_server.py
slimHTTP-1.0.1rc7.dist-info/LICENSE
slimHTTP-1.0.1rc7.dist-info/METADATA
slimHTTP-1.0.1rc7.dist-info/WHEEL
slimHTTP-1.0.1rc7.dist-info/top_level.txt
slimHTTP-1.0.1rc7.dist-info/RECORD
