Metadata-Version: 2.1
Name: slimHTTP
Version: 1.0.1rc7
Summary: A minimalistic non-threaded HTTP server written in Python. Supports REST & WebSockets¹.
Home-page: https://github.com/Torxed/slimHTTP
Author: Anton Hvornum
Author-email: anton@hvornum.se
License: UNKNOWN
Platform: UNKNOWN
Classifier: Programming Language :: Python :: 3.8
Classifier: License :: OSI Approved :: GNU General Public License v3 (GPLv3)
Classifier: Operating System :: POSIX
Classifier: Operating System :: Microsoft
Requires-Python: >=3.8
